大二下/计算机组成原理/students/mbinary/verilog/fsm/alu.v
module alu(
        input         [31:0] alu_a,
		input         [31:0] alu_b,
		input 		  [4:0] alu_op,
		output 	reg   [31:0] res);

		always@(*)
		begin
			case(alu_op)
			0:res=0;
			1:res=alu_a+alu_b;
			2:res=alu_a-alu_b;
			3:res=alu_a&alu_b;
			4:res=alu_a|alu_b;
			5:res=alu_a ^ alu_b;
			6:res= ~(alu_a|alu_b);

			endcase
		end
endmodule

大二下/计算机组成原理/students/mbinary/verilog/reg/reg1.v
module regfile(
    input           clk,
    input           rst_n,
    input	[5:0]	rAddr1,
    output  [31:0]	rDout1,
    input	[5:0]	wAddr,
    input	[31:0]  wDin,
    input			wEna
);

reg [31:0]  data  [0:63];
reg [31:0] tmp ;

initial begin
data[0] = 2 ;
data[1] = 2 ;
data[2] = 0 ;
data[3] = 0 ;
data[4] = 0 ;
data[5] = 0 ;
data[6] = 0 ;
data[7] = 0 ;
data[8] = 0 ;
data[9] = 0 ;
data[10] = 0 ;
data[11] = 0 ;
data[12] = 0 ;
data[13] = 0 ;
data[14] = 0 ;
data[15] = 0 ;
data[16] = 0 ;
data[17] = 0 ;
data[18] = 0 ;
data[19] = 0 ;
data[20] = 0 ;
data[21] = 0 ;
data[22] = 0 ;
data[23] = 0 ;
data[24] = 0 ;
data[25] = 0 ;
data[26] = 0 ;
data[27] = 0 ;
data[28] = 0 ;
data[29] = 0 ;
data[30] = 0 ;
data[31] = 0 ;
data[32] = 0 ;
data[33] = 0 ;
data[34] = 0 ;
data[35] = 0 ;
data[36] = 0 ;
data[37] = 0 ;
data[38] = 0 ;
data[39] = 0 ;
data[40] = 0 ;
data[41] = 0 ;
data[42] = 0 ;
data[43] = 0 ;
data[44] = 0 ;
data[45] = 0 ;
data[46] = 0 ;
data[47] = 0 ;
data[48] = 0 ;
data[49] = 0 ;
data[50] = 0 ;
data[51] = 0 ;
data[52] = 0 ;
data[53] = 0 ;
data[54] = 0 ;
data[55] = 0 ;
data[56] = 0 ;
data[57] = 0 ;
data[58] = 0 ;
data[59] = 0 ;
data[60] = 0 ;
data[61] = 0 ;
data[62] = 0 ;
data[63] = 0 ;
end

assign rDout1 = tmp;

always@(*)
    if(rAddr1 == wAddr && wEna) tmp  = wDin;
    else tmp = data[rAddr1];
    
always@(posedge clk , negedge rst_n)
    begin
        if(~rst_n ) begin
        data[0] = 2 ;
        data[1] = 2 ;
        data[2] = 0 ;
        data[3] = 0 ;
        data[4] = 0 ;
        data[5] = 0 ;
        data[6] = 0 ;
        data[7] = 0 ;
        data[8] = 0 ;
        data[9] = 0 ;
        data[10] = 0 ;
        data[11] = 0 ;
        data[12] = 0 ;
        data[13] = 0 ;
        data[14] = 0 ;
        data[15] = 0 ;
        data[16] = 0 ;
        data[17] = 0 ;
        data[18] = 0 ;
        data[19] = 0 ;
        data[20] = 0 ;
        data[21] = 0 ;
        data[22] = 0 ;
        data[23] = 0 ;
        data[24] = 0 ;
        data[25] = 0 ;
        data[26] = 0 ;
        data[27] = 0 ;
        data[28] = 0 ;
        data[29] = 0 ;
        data[30] = 0 ;
        data[31] = 0 ;
        data[32] = 0 ;
        data[33] = 0 ;
        data[34] = 0 ;
        data[35] = 0 ;
        data[36] = 0 ;
        data[37] = 0 ;
        data[38] = 0 ;
        data[39] = 0 ;
        data[40] = 0 ;
        data[41] = 0 ;
        data[42] = 0 ;
        data[43] = 0 ;
        data[44] = 0 ;
        data[45] = 0 ;
        data[46] = 0 ;
        data[47] = 0 ;
        data[48] = 0 ;
        data[49] = 0 ;
        data[50] = 0 ;
        data[51] = 0 ;
        data[52] = 0 ;
        data[53] = 0 ;
        data[54] = 0 ;
        data[55] = 0 ;
        data[56] = 0 ;
        data[57] = 0 ;
        data[58] = 0 ;
        data[59] = 0 ;
        data[60] = 0 ;
        data[61] = 0 ;
        data[62] = 0 ;
        data[63] = 0 ;
        end
        else
            data[wAddr] = wEna ? wDin: data[wAddr];
end

endmodule

大二下/计算机组成原理/students/mbinary/verilog/reg/control.v
module control(
    input clk,rst_n,
    output wEna,
    output [5:0] r1,w
    );
    reg  [5:0] ct =1;
    
    assign wEna = 1;
    assign  r1 = ct,
			w = ct+1;
    
    always@(posedge clk,negedge rst_n)
        begin
            if(~rst_n || ct==63) ct=1;
            else ct =ct+1;
        end
endmodule

大二下/计算机组成原理/students/mbinary/verilog/reg/top.v
`timescale 1ns / 1ps

module top(
    input           clk,
    input           rst_n,
    output  [31:0] oa,ob,oc
);


wire [5:0]	rAddr1, wAddr;
wire [31:0] rdata,w;
reg [31:0] tmp=0,sum = 2;
wire wEna;
reg [31:0] res=2;

control ctrl(clk,rst_n, wEna , rAddr1,wAddr);

regfile  regfile(clk,rst_n,rAddr1,rdata,wAddr,sum,wEna);
alu alu(tmp,rdata,1,w);
assign oa = tmp,
        ob = rdata,
        oc = res;
always @(posedge clk) res = w;
//always @*
//$display("in top: tmp,t,rdata,sum,w,raddr= %g,%g,%g,%g,%g",tmp,t,rdata,sum,w,rAddr1);
always @(negedge clk)
    begin 
        tmp <=rdata;
        sum <= w;
        
    end



endmodule

大二下/计算机组成原理/students/mbinary/verilog/reg/test.v
`timescale 1ns / 1ps


module test();

initial begin 
	$dumpfile("test.vcd");
	$dumpvars(1,test);
	end

 reg clk=0;
 reg [6:0] ct=0;
   reg rst_n = 1;
   wire [31:0] a,b,c;
    top top(clk,rst_n,a,b,c);
always #100 
    begin 
        if(ct==20) $finish;
        else begin 
        ct=ct+1 ;   
        clk=~clk; 
        
        end
   end 
always #200 $display("in sim: %g + %g = %g , At time %t", a,b,c,$time);
endmodule

大二下/计算机组成原理/students/mbinary/verilog/reg/sim.v
`timescale 1ns / 1ps


module sim();

initial begin 
	$dumpfile("reg.vcd");
	$dumpvars(1,sim);
	end

 reg clk=0;
 reg [6:0] ct=0;
   reg rst_n = 1;
   wire [31:0] a,b,c;
    top top(clk,rst_n,a,b,c);
always #100 
    begin 
        if(ct==20) $finish;
        else begin 
        ct=ct+1 ;   
        clk=~clk; 
        
        end
    end 
always #200 $display("in sim: %g + %g = %g , At time %t", a,b,c,$time);
endmodule

大二下/计算机组成原理/students/mbinary/verilog/reg/reg.vcd
$date
	Wed Apr 11 23:42:23 2018
$end
$version
	Icarus Verilog
$end
$timescale
	1ps
$end
$scope module sim $end
$var wire 32 ! a [31:0] $end
$var wire 32 " b [31:0] $end
$var wire 32 # c [31:0] $end
$var reg 1 $ clk $end
$var reg 7 % ct [6:0] $end
$var reg 1 & rst_n $end
$upscope $end
$scope module test $end
$var wire 32 ' a [31:0] $end
$var wire 32 ( b [31:0] $end
$var wire 32 ) c [31:0] $end
$var reg 1 * clk $end
$var reg 7 + ct [6:0] $end
$var reg 1 , rst_n $end
$upscope $end
$enddefinitions $end
#0
$dumpvars
1,
b0 +
0*
b10 )
b10 (
b10 '
1&
b0 %
0$
b10 #
b10 "
b10 !
$end
#100000
b100 )
b100 #
1*
b1 +
1$
b1 %
#200000
0*
b10 +
0$
b10 %
#300000
b100 (
b100 "
1*
b11 +
1$
b11 %
#400000
b100 '
b100 !
0*
b100 +
0$
b100 %
#500000
b110 (
b110 "
b1000 )
b1000 #
1*
b101 +
1$
b101 %
#600000
b110 '
b110 !
0*
b110 +
0$
b110 %
#700000
b1010 (
b1010 "
b1100 )
b1100 #
1*
b111 +
1$
b111 %
#800000
b1010 '
b1010 !
0*
b1000 +
0$
b1000 %
#900000
b10000 (
b10000 "
b10100 )
b10100 #
1*
b1001 +
1$
b1001 %
#1000000
b10000 '
b10000 !
0*
b1010 +
0$
b1010 %
#1100000
b11010 (
b11010 "
b100000 )
b100000 #
1*
b1011 +
1$
b1011 %
#1200000
b11010 '
b11010 !
0*
b1100 +
0$
b1100 %
#1300000
b101010 (
b101010 "
b110100 )
b110100 #
1*
b1101 +
1$
b1101 %
#1400000
b101010 '
b101010 !
0*
b1110 +
0$
b1110 %
#1500000
b1000100 (
b1000100 "
b1010100 )
b1010100 #
1*
b1111 +
1$
b1111 %
#1600000
b1000100 '
b1000100 !
0*
b10000 +
0$
b10000 %
#1700000
b1101110 (
b1101110 "
b10001000 )
b10001000 #
1*
b10001 +
1$
b10001 %
#1800000
b1101110 '
b1101110 !
0*
b10010 +
0$
b10010 %
#1900000
b10110010 (
b10110010 "
b11011100 )
b11011100 #
1*
b10011 +
1$
b10011 %
#2000000
b10110010 '
b10110010 !
0*
b10100 +
0$
b10100 %
