大二下/计算机组成原理/students/mbinary/verilog/fsm/ram.v
module ram(
    input clk,
    input  w_en,useless,
    input [7:0] w_addr,
    input [31:0]res,
    input useless2,r_en,
    input [7:0] r_addr,
    output reg[31:0] r_data
    );


	reg [31:0] data [0:255];

    
    initial begin
    data[0] = 10;
data[1] = 11;
data[2] = 12;
data[3] = 13;
data[4] = 14;
data[5] = 15;
data[6] = 16;
data[7] = 17;
data[8] = 18;
data[9] = 19;
data[10] = 20;
data[11] = 21;
data[12] = 22;
data[13] = 23;
data[14] = 0;
data[15] = 0;
data[16] = 0;
data[17] = 0;
data[18] = 0;
data[19] = 0;
data[20] = 0;
data[21] = 0;
data[22] = 0;
data[23] = 0;
data[24] = 0;
data[25] = 0;
data[26] = 0;
data[27] = 0;
data[28] = 0;
data[29] = 0;
data[30] = 0;
data[31] = 0;
data[32] = 0;
data[33] = 0;
data[34] = 0;
data[35] = 0;
data[36] = 0;
data[37] = 0;
data[38] = 0;
data[39] = 0;
data[40] = 0;
data[41] = 0;
data[42] = 0;
data[43] = 0;
data[44] = 0;
data[45] = 0;
data[46] = 0;
data[47] = 0;
data[48] = 0;
data[49] = 0;
data[50] = 0;
data[51] = 0;
data[52] = 0;
data[53] = 0;
data[54] = 0;
data[55] = 0;
data[56] = 0;
data[57] = 0;
data[58] = 0;
data[59] = 0;
data[60] = 0;
data[61] = 0;
data[62] = 0;
data[63] = 0;
data[64] = 0;
data[65] = 0;
data[66] = 0;
data[67] = 0;
data[68] = 0;
data[69] = 0;
data[70] = 0;
data[71] = 0;
data[72] = 0;
data[73] = 0;
data[74] = 0;
data[75] = 0;
data[76] = 0;
data[77] = 0;
data[78] = 0;
data[79] = 0;
data[80] = 0;
data[81] = 0;
data[82] = 0;
data[83] = 0;
data[84] = 0;
data[85] = 0;
data[86] = 0;
data[87] = 0;
data[88] = 0;
data[89] = 0;
data[90] = 0;
data[91] = 0;
data[92] = 0;
data[93] = 0;
data[94] = 0;
data[95] = 0;
data[96] = 0;
data[97] = 0;
data[98] = 0;
data[99] = 0;
data[100] = 0;
data[101] = 1;
data[102] = 2;
data[103] = 3;
data[104] = 4;
data[105] = 5;
data[106] = 6;
data[107] = -1;
end
	always@(*)begin
		if(w_en)data[w_addr] = res;
        else data[w_addr]=data[w_addr];
        if(r_en)r_data = data[r_addr];
        else r_data = 0;
    end
endmodule

大二下/计算机组成原理/students/mbinary/verilog/fsm/control.v
module control(
    input clk,rst,
    output reg  w_en,
    output reg [7:0] w_addr,
    output reg r_en,
    output reg [7:0] r_addr,
    input [31:0] r_data,
    output reg [31:0] a,b,
    output reg [4:0]op
    );
    
    /* port */
/* reg w_en,r_en;
reg [5:0] r_addr,w_addr;
reg [31:0] r_data,a,b;
reg [4:0] op; */

/* inner */
reg [7:0] addr1,addr2,addr3;
reg [3:0] cur_st = 0, next_st=0;// 1,2,3,4,5


always@(posedge clk or posedge rst)
begin
    if(rst)
        cur_st = 0;
    else 
        cur_st = next_st;
end

always@(*)
    case(cur_st)
        1:next_st=2;
        2:next_st=3;
        3:next_st=4;
        4:if(r_data==-1) next_st=0; else next_st=5;
        5:next_st=1;
        default:next_st = 1;
    endcase
    
always@(negedge clk or posedge rst)
    if(rst||cur_st==0)begin
        w_en<=0;
        r_en<=1;
        addr1<=0;
        addr2 <= 100;
        addr3<=200;
        r_addr<=0;
        w_addr<=0;
        a<=0;
        b<=0;
    end else if(cur_st==1) begin
        w_en<=0;
        r_en<=1;
        addr1 <= addr1+1;
        r_addr <= addr1;
     end else if (cur_st==2) begin
        w_en<=0;
        r_en<=1;
        addr1 <= addr1+1;
        r_addr <= addr1;
        a<=r_data;
    end else if (cur_st==3) begin
        w_en<=0;
        r_en<=1;
        addr2 <= addr2+1;
        r_addr <= addr2;
        b<=r_data;
    end else if (cur_st==4) begin
        w_en<=0;
        r_en<=0;
        op<=r_data;
    end else if(cur_st==5) begin
        w_en<=1;
        r_en<=0;
        addr3 = addr3+1;
        w_addr <= addr3;
    end
    
endmodule

大二下/计算机组成原理/students/mbinary/verilog/fsm/alu.v
module alu(
        input         [31:0] alu_a,
		input         [31:0] alu_b,
		input 		  [4:0] alu_op,
		output 	reg   [31:0] res);

		always@(*)
		begin
			case(alu_op)
			0:res=0;
			1:res=alu_a+alu_b;
			2:res=alu_a-alu_b;
			3:res=alu_a&alu_b;
			4:res=alu_a|alu_b;
			5:res=alu_a ^ alu_b;
			6:res= ~(alu_a|alu_b);

			endcase
		end
endmodule

大二下/计算机组成原理/students/mbinary/verilog/fsm/top.v
module top(
    input wire clk,
    input wire rst
    );
    
wire w_en,r_en;
wire [7:0] r_addr,w_addr;
wire [31:0] r_data,a,b,res;
wire [4:0] op;
alu alu1(a,b,op,res);
control ctrl1(clk,rst,w_en,w_addr,r_en,r_addr,r_data,a,b,op);
ram ram1(clk,w_en,1,w_addr,res,clk,r_en,r_addr,r_data);
endmodule


/* 
初始化,
检查control中的状态, 传给top, 前3个周期读,
此时也是通过control传递en, addr, 等信息,
将得到的输入信息传到control后,用导线?连接到alu,
alu再将计算结果传回control,
由control再写ram
 */

大二下/计算机组成原理/students/mbinary/verilog/fsm/test.v
module test();
    
reg clk=0,rst=0;

initial begin 
    $dumpfile("test.vcd");
    $dumpvars(0,test);
    #1000 ;
    $finish;
end

top top1(clk,rst);

always #10 
begin 
    clk = ~clk;
end


endmodule

大二下/计算机组成原理/students/mbinary/verilog/fsm/test.vcd
$date
	Thu Apr 19 19:10:36 2018
$end
$version
	Icarus Verilog
$end
$timescale
	1s
$end
$scope module test $end
$var reg 1 ! clk $end
$var reg 1 " rst $end
$scope module top1 $end
$var wire 32 # a [31:0] $end
$var wire 32 $ b [31:0] $end
$var wire 1 % clk $end
$var wire 5 & op [4:0] $end
$var wire 8 ' r_addr [7:0] $end
$var wire 32 ( r_data [31:0] $end
$var wire 1 ) r_en $end
$var wire 32 * res [31:0] $end
$var wire 1 + rst $end
$var wire 8 , w_addr [7:0] $end
$var wire 1 - w_en $end
$scope module alu1 $end
$var wire 32 . alu_a [31:0] $end
$var wire 32 / alu_b [31:0] $end
$var wire 5 0 alu_op [4:0] $end
$var reg 32 1 res [31:0] $end
$upscope $end
$scope module ctrl1 $end
$var wire 1 % clk $end
$var wire 32 2 r_data [31:0] $end
$var wire 1 + rst $end
$var reg 32 3 a [31:0] $end
$var reg 8 4 addr1 [7:0] $end
$var reg 8 5 addr2 [7:0] $end
$var reg 8 6 addr3 [7:0] $end
$var reg 32 7 b [31:0] $end
$var reg 4 8 cur_st [3:0] $end
$var reg 4 9 next_st [3:0] $end
$var reg 5 : op [4:0] $end
$var reg 8 ; r_addr [7:0] $end
$var reg 1 < r_en $end
$var reg 8 = w_addr [7:0] $end
$var reg 1 > w_en $end
$upscope $end
$scope module ram1 $end
$var wire 1 % clk $end
$var wire 8 ? r_addr [7:0] $end
$var wire 1 ) r_en $end
$var wire 32 @ res [31:0] $end
$var wire 1 A useless $end
$var wire 1 % useless2 $end
$var wire 8 B w_addr [7:0] $end
$var wire 1 - w_en $end
$var reg 32 C r_data [31:0] $end
$upscope $end
$upscope $end
$upscope $end
$enddefinitions $end
#0
$dumpvars
b1010 C
b0 B
1A
bx @
b0 ?
0>
b0 =
1<
b0 ;
bx :
b1 9
b0 8
b0 7
b11001000 6
b1100100 5
b0 4
b0 3
b1010 2
bx 1
bx 0
b0 /
b0 .
0-
b0 ,
0+
bx *
1)
b1010 (
b0 '
bx &
0%
b0 $
b0 #
0"
0!
$end
#10
b10 9
b1 8
1!
1%
#20
b1 4
0!
0%
#30
b11 9
b10 8
1!
1%
#40
b1011 C
b1011 (
b1011 2
b1010 3
b1010 #
b1010 .
b1 ;
b1 '
b1 ?
b10 4
0!
0%
#50
b100 9
b11 8
1!
1%
#60
b0 C
b0 (
b0 2
b1011 7
b1011 $
b1011 /
b1100100 ;
b1100100 '
b1100100 ?
b1100101 5
0!
0%
#70
b101 9
b100 8
1!
1%
#80
b0 1
b0 *
b0 @
b0 :
b0 &
b0 0
0<
0)
0!
0%
#90
b1 9
b101 8
1!
1%
#100
b11001001 =
b11001001 ,
b11001001 B
1>
1-
b11001001 6
0!
0%
#110
b10 9
b1 8
1!
1%
#120
b1100 C
b1100 (
b1100 2
b10 ;
b10 '
b10 ?
b11 4
1<
1)
0>
0-
0!
0%
#130
b11 9
b10 8
1!
1%
#140
b1101 C
b1101 (
b1101 2
b1100 3
b1100 #
b1100 .
b11 ;
b11 '
b11 ?
b100 4
0!
0%
#150
b100 9
b11 8
1!
1%
#160
b1 C
b1 (
b1 2
b1101 7
b1101 $
b1101 /
b1100101 ;
b1100101 '
b1100101 ?
b1100110 5
0!
0%
#170
b101 9
b100 8
1!
1%
#180
b11001 1
b11001 *
b11001 @
b0 C
b0 (
b0 2
b1 :
b1 &
b1 0
0<
0)
0!
0%
#190
b1 9
b101 8
1!
1%
#200
b11001010 =
b11001010 ,
b11001010 B
1>
1-
b11001010 6
0!
0%
#210
b10 9
b1 8
1!
1%
#220
b1110 C
b1110 (
b1110 2
b100 ;
b100 '
b100 ?
b101 4
1<
1)
0>
0-
0!
0%
#230
b11 9
b10 8
1!
1%
#240
b11011 1
b11011 *
b11011 @
b1111 C
b1111 (
b1111 2
b1110 3
b1110 #
b1110 .
b101 ;
b101 '
b101 ?
b110 4
0!
0%
#250
b100 9
b11 8
1!
1%
#260
b11101 1
b11101 *
b11101 @
b10 C
b10 (
b10 2
b1111 7
b1111 $
b1111 /
b1100110 ;
b1100110 '
b1100110 ?
b1100111 5
0!
0%
#270
b101 9
b100 8
1!
1%
#280
b11111111111111111111111111111111 1
b11111111111111111111111111111111 *
b11111111111111111111111111111111 @
b0 C
b0 (
b0 2
b10 :
b10 &
b10 0
0<
0)
0!
0%
#290
b1 9
b101 8
1!
1%
#300
b11001011 =
b11001011 ,
b11001011 B
1>
1-
b11001011 6
0!
0%
#310
b10 9
b1 8
1!
1%
#320
b10000 C
b10000 (
b10000 2
b110 ;
b110 '
b110 ?
b111 4
1<
1)
0>
0-
0!
0%
#330
b11 9
b10 8
1!
1%
#340
b1 1
b1 *
b1 @
b10001 C
b10001 (
b10001 2
b10000 3
b10000 #
b10000 .
b111 ;
b111 '
b111 ?
b1000 4
0!
0%
#350
b100 9
b11 8
1!
1%
#360
b11111111111111111111111111111111 1
b11111111111111111111111111111111 *
b11111111111111111111111111111111 @
b11 C
b11 (
b11 2
b10001 7
b10001 $
b10001 /
b1100111 ;
b1100111 '
b1100111 ?
b1101000 5
0!
0%
#370
b101 9
b100 8
1!
1%
#380
b10000 1
b10000 *
b10000 @
b0 C
b0 (
b0 2
b11 :
b11 &
b11 0
0<
0)
0!
0%
#390
b1 9
b101 8
1!
1%
#400
b11001100 =
b11001100 ,
b11001100 B
1>
1-
b11001100 6
0!
0%
#410
b10 9
b1 8
1!
1%
#420
b10010 C
b10010 (
b10010 2
b1000 ;
b1000 '
b1000 ?
b1001 4
1<
1)
0>
0-
0!
0%
#430
b11 9
b10 8
1!
1%
#440
b10011 C
b10011 (
b10011 2
b10010 3
b10010 #
b10010 .
b1001 ;
b1001 '
b1001 ?
b1010 4
0!
0%
#450
b100 9
b11 8
1!
1%
#460
b10010 1
b10010 *
b10010 @
b100 C
b100 (
b100 2
b10011 7
b10011 $
b10011 /
b1101000 ;
b1101000 '
b1101000 ?
b1101001 5
0!
0%
#470
b101 9
b100 8
1!
1%
#480
b10011 1
b10011 *
b10011 @
b0 C
b0 (
b0 2
b100 :
b100 &
b100 0
0<
0)
0!
0%
#490
b1 9
b101 8
1!
1%
#500
b11001101 =
b11001101 ,
b11001101 B
1>
1-
b11001101 6
0!
0%
#510
b10 9
b1 8
1!
1%
#520
b10100 C
b10100 (
b10100 2
b1010 ;
b1010 '
b1010 ?
b1011 4
1<
1)
0>
0-
0!
0%
#530
b11 9
b10 8
1!
1%
#540
b10111 1
b10111 *
b10111 @
b10101 C
b10101 (
b10101 2
b10100 3
b10100 #
b10100 .
b1011 ;
b1011 '
b1011 ?
b1100 4
0!
0%
#550
b100 9
b11 8
1!
1%
#560
b10101 1
b10101 *
b10101 @
b101 C
b101 (
b101 2
b10101 7
b10101 $
b10101 /
b1101001 ;
b1101001 '
b1101001 ?
b1101010 5
0!
0%
#570
b101 9
b100 8
1!
1%
#580
b1 1
b1 *
b1 @
b0 C
b0 (
b0 2
b101 :
b101 &
b101 0
0<
0)
0!
0%
#590
b1 9
b101 8
1!
1%
#600
b11001110 =
b11001110 ,
b11001110 B
1>
1-
b11001110 6
0!
0%
#610
b10 9
b1 8
1!
1%
#620
b10110 C
b10110 (
b10110 2
b1100 ;
b1100 '
b1100 ?
b1101 4
1<
1)
0>
0-
0!
0%
#630
b11 9
b10 8
1!
1%
#640
b11 1
b11 *
b11 @
b10111 C
b10111 (
b10111 2
b10110 3
b10110 #
b10110 .
b1101 ;
b1101 '
b1101 ?
b1110 4
0!
0%
#650
b100 9
b11 8
1!
1%
#660
b1 1
b1 *
b1 @
b110 C
b110 (
b110 2
b10111 7
b10111 $
b10111 /
b1101010 ;
b1101010 '
b1101010 ?
b1101011 5
0!
0%
#670
b101 9
b100 8
1!
1%
#680
b11111111111111111111111111101000 1
b11111111111111111111111111101000 *
b11111111111111111111111111101000 @
b0 C
b0 (
b0 2
b110 :
b110 &
b110 0
0<
0)
0!
0%
#690
b1 9
b101 8
1!
1%
#700
b11001111 =
b11001111 ,
b11001111 B
1>
1-
b11001111 6
0!
0%
#710
b10 9
b1 8
1!
1%
#720
b1110 ;
b1110 '
b1110 ?
b1111 4
1<
1)
0>
0-
0!
0%
#730
b11 9
b10 8
1!
1%
#740
b0 3
b0 #
b0 .
b1111 ;
b1111 '
b1111 ?
b10000 4
0!
0%
#750
b100 9
b11 8
1!
1%
#760
b11111111111111111111111111111111 1
b11111111111111111111111111111111 *
b11111111111111111111111111111111 @
b11111111111111111111111111111111 C
b11111111111111111111111111111111 (
b11111111111111111111111111111111 2
b0 7
b0 $
b0 /
b1101011 ;
b1101011 '
b1101011 ?
b1101100 5
0!
0%
#770
b0 9
b100 8
1!
1%
#780
b101 9
b0 C
b0 (
b0 2
b11111 :
b11111 &
b11111 0
0<
0)
0!
0%
#790
b1 9
b101 8
1!
1%
#800
b11010000 =
b11010000 ,
b11010000 B
1>
1-
b11010000 6
0!
0%
#810
b10 9
b1 8
1!
1%
#820
b10000 ;
b10000 '
b10000 ?
b10001 4
1<
1)
0>
0-
0!
0%
#830
b11 9
b10 8
1!
1%
#840
b10001 ;
b10001 '
b10001 ?
b10010 4
0!
0%
#850
b100 9
b11 8
1!
1%
#860
bx C
bx (
bx 2
b1101100 ;
b1101100 '
b1101100 ?
b1101101 5
0!
0%
#870
b101 9
b100 8
1!
1%
#880
b0 C
b0 (
b0 2
bx :
bx &
bx 0
0<
0)
0!
0%
#890
b1 9
b101 8
1!
1%
#900
b11010001 =
b11010001 ,
b11010001 B
1>
1-
b11010001 6
0!
0%
#910
b10 9
b1 8
1!
1%
#920
b10010 ;
b10010 '
b10010 ?
b10011 4
1<
1)
0>
0-
0!
0%
#930
b11 9
b10 8
1!
1%
#940
b10011 ;
b10011 '
b10011 ?
b10100 4
0!
0%
#950
b100 9
b11 8
1!
1%
#960
bx C
bx (
bx 2
b1101101 ;
b1101101 '
b1101101 ?
b1101110 5
0!
0%
#970
b101 9
b100 8
1!
1%
#980
b0 C
b0 (
b0 2
0<
0)
0!
0%
#990
b1 9
b101 8
1!
1%
#1000
b11010010 =
b11010010 ,
b11010010 B
1>
1-
b11010010 6
0!
0%
